easy_mirrors/__about__.py
easy_mirrors/__init__.py
easy_mirrors/__main__.py
easy_mirrors/api.py
easy_mirrors/config.py
easy_mirrors/defaults.py
easy_mirrors/exceptions.py
easy_mirrors/fields.py
easy_mirrors/git_repository.py
easy_mirrors/logger_wrapper.py
easy_mirrors/py.typed
easy_mirrors-0.3.2.dist-info/LICENSE
easy_mirrors-0.3.2.dist-info/METADATA
easy_mirrors-0.3.2.dist-info/WHEEL
easy_mirrors-0.3.2.dist-info/entry_points.txt
easy_mirrors-0.3.2.dist-info/RECORD
