Metadata-Version: 2.3
Name: easy-mirrors
Version: 0.3.2
Summary: Simplest way to backup and restore git repositories
License: MIT
Keywords: automation,git
Author: Vladislav Punko
Author-email: iam.vlad.punko@gmail.com
Requires-Python: >=3.10,<4.0
Classifier: Intended Audience :: Developers
Classifier: Intended Audience :: System Administrators
Classifier: Operating System :: OS Independent
Classifier: Topic :: Software Development :: Libraries :: Python Modules
Classifier: Topic :: Software Development :: Libraries
Classifier: Topic :: Software Development
Classifier: Topic :: Utilities
Classifier: Typing :: Typed
Classifier: License :: OSI Approved :: MIT License
Classifier: Programming Language :: Python :: 3
Classifier: Programming Language :: Python :: 3.10
Classifier: Programming Language :: Python :: 3.11
Classifier: Programming Language :: Python :: 3.12
Project-URL: Issue tracker, https://github.com/vladpunko/easy-mirrors/issues
Project-URL: Source code, https://github.com/vladpunko/easy-mirrors
